nlp2scryfall/__init__.py
nlp2scryfall/scryfall_api.py
nlp2scryfall/translator.py
nlp2scryfall/parsers/__init__.py
nlp2scryfall/parsers/card_properties.py
nlp2scryfall/parsers/core.py
nlp2scryfall/parsers/metadata.py
nlp2scryfall/parsers/numerical.py
nlp2scryfall/parsers/special.py
nlp2scryfall/parsers/text.py
nlp2scryfall-0.1.0.dist-info/METADATA
nlp2scryfall-0.1.0.dist-info/WHEEL
nlp2scryfall-0.1.0.dist-info/licenses/LICENSE
nlp2scryfall-0.1.0.dist-info/RECORD
