Metadata-Version: 2.4
Name: nlp2scryfall
Version: 0.1.0
Summary: Translate natural language queries to Scryfall search syntax
Project-URL: Homepage, https://github.com/raphaelchazelle/nlp2scryfall
Project-URL: Repository, https://github.com/raphaelchazelle/nlp2scryfall
Project-URL: Issues, https://github.com/raphaelchazelle/nlp2scryfall/issues
Author-email: Raphael Chazelle <raphael@example.com>
License: MIT
License-File: LICENSE
Classifier: Development Status :: 3 - Alpha
Classifier: Intended Audience :: Developers
Classifier: License :: OSI Approved :: MIT License
Classifier: Programming Language :: Python :: 3
Classifier: Programming Language :: Python :: 3.8
Classifier: Programming Language :: Python :: 3.9
Classifier: Programming Language :: Python :: 3.10
Classifier: Programming Language :: Python :: 3.11
Classifier: Programming Language :: Python :: 3.12
Classifier: Topic :: Software Development :: Libraries :: Python Modules
Classifier: Topic :: Text Processing :: Linguistic
Requires-Python: >=3.8
Requires-Dist: requests>=2.25.0
Requires-Dist: typing-extensions>=4.0.0
